fastapi_ui_auth-0.2.0.dist-info/licenses/LICENSE
uiauth/__init__.py
uiauth/endpoints.py
uiauth/enums.py
uiauth/logger.py
uiauth/models.py
uiauth/secure.py
uiauth/service.py
uiauth/utils.py
uiauth/version.py
uiauth/templates/index.html
uiauth/templates/session.html
uiauth/templates/unauthorized.html
fastapi_ui_auth-0.2.0.dist-info/METADATA
fastapi_ui_auth-0.2.0.dist-info/WHEEL
fastapi_ui_auth-0.2.0.dist-info/top_level.txt
fastapi_ui_auth-0.2.0.dist-info/RECORD
